setup.cfg
setup.py
Meritocracy.egg-info/PKG-INFO
Meritocracy.egg-info/SOURCES.txt
Meritocracy.egg-info/dependency_links.txt
Meritocracy.egg-info/entry_points.txt
Meritocracy.egg-info/requires.txt
Meritocracy.egg-info/top_level.txt
Meritocracy.egg-info/zip-safe
meritocracy/__init__.py
meritocracy/meta.py
meritocracy/models.py