Metadata-Version: 1.0
Name: Meritocracy
Version: 0.1
Summary: Tool to access contribution statistics from a revision control system.
Home-page: http://douglas.mayle.org
Author: Douglas Mayle
Author-email: UNKNOWN
License: LGPL
Platform: UNKNOWN
